limitpal/__init__.py
limitpal/exceptions.py
limitpal/base/__init__.py
limitpal/base/async_.py
limitpal/base/sync.py
limitpal/composite/__init__.py
limitpal/composite/async_.py
limitpal/composite/sync.py
limitpal/limiters/__init__.py
limitpal/limiters/async_/__init__.py
limitpal/limiters/async_/leaky_bucket.py
limitpal/limiters/async_/token_bucket.py
limitpal/limiters/sync/__init__.py
limitpal/limiters/sync/leaky_bucket.py
limitpal/limiters/sync/token_bucket.py
limitpal/resilience/__init__.py
limitpal/resilience/circuit_breaker.py
limitpal/resilience/executor_async.py
limitpal/resilience/executor_sync.py
limitpal/resilience/retry.py
limitpal/time/__init__.py
limitpal/time/clock.py
limitpal-0.1.0.dist-info/METADATA
limitpal-0.1.0.dist-info/WHEEL
limitpal-0.1.0.dist-info/licenses/LICENSE
limitpal-0.1.0.dist-info/RECORD
