Metadata-Version: 2.4
Name: limitpal
Version: 0.1.0
Summary: A collection of fast, modular rate & concurrency limiters for Python async and sync code.
Project-URL: Homepage, https://github.com/Guli-vali/limitpal
Project-URL: Repository, https://github.com/Guli-vali/limitpal
Project-URL: Issues, https://github.com/Guli-vali/limitpal/issues
Project-URL: Documentation, https://github.com/Guli-vali/limitpal#readme
Author: Ilya Masliev
License: MIT
License-File: LICENSE
Keywords: asyncio,concurrency,leaky-bucket,limiter,rate-limit,throttle,token-bucket
Classifier: Development Status :: 4 - Beta
Classifier: Framework :: AsyncIO
Classifier: Intended Audience :: Developers
Classifier: License :: OSI Approved :: MIT License
Classifier: Operating System :: OS Independent
Classifier: Programming Language :: Python :: 3
Classifier: Programming Language :: Python :: 3.10
Classifier: Programming Language :: Python :: 3.11
Classifier: Programming Language :: Python :: 3.12
Classifier: Programming Language :: Python :: 3.13
Classifier: Topic :: Software Development :: Libraries :: Python Modules
Classifier: Typing :: Typed
Requires-Python: >=3.10
